prince_text_detection/__init__.py
prince_text_detection/prince_text_detection.py
prince_text_detection-0.0.2.dist-info/DESCRIPTION.rst
prince_text_detection-0.0.2.dist-info/METADATA
prince_text_detection-0.0.2.dist-info/RECORD
prince_text_detection-0.0.2.dist-info/WHEEL
prince_text_detection-0.0.2.dist-info/metadata.json
prince_text_detection-0.0.2.dist-info/top_level.txt
